tktimer/__init__.py
tktimer/tktimer.py
tktimer-0.1.0.dist-info/LICENSE
tktimer-0.1.0.dist-info/WHEEL
tktimer-0.1.0.dist-info/METADATA
tktimer-0.1.0.dist-info/RECORD
