Metadata-Version: 2.1
Name: tktimer
Version: 0.1.0
Summary: Timer (stopwatch and countdown) widgets for tkinter
License: MIT
Author: adder46
Author-email: dedmauz69@gmail.com
Requires-Python: >=3.6,<4.0
Classifier: License :: OSI Approved :: MIT License
Classifier: Programming Language :: Python :: 3
Classifier: Programming Language :: Python :: 3.6
Classifier: Programming Language :: Python :: 3.7
Classifier: Programming Language :: Python :: 3.8
Classifier: Programming Language :: Python :: 3.9
